Metadata-Version: 1.0
Name: ms-distributions-2022
Version: 0.2
Summary: Gaussian and Binomial distributions
Home-page: UNKNOWN
Author: Maximilian Schulz
Author-email: maxi.schulz@gmx.net
License: UNKNOWN
Platform: UNKNOWN
